.gitignore
LICENSE
MANIFEST.in
README
requirements.txt
setup.py
doc_src/Makefile
doc_src/conf.py
doc_src/getting_started.rst
doc_src/index.rst
doc_src/installation.rst
doc_src/make.bat
doc_src/one_blog_or_many.rst
doc_src/relating_arbitrary_models.rst
doc_src/specifying_urls.rst
doc_src/_static/breadcrumb_background.png
doc_src/_static/default.css
doc_src/_static/documentation.png
doc_src/_static/header_sm_mid.png
doc_src/_static/scrn1.png
doc_src/_static/scrn2.png
doc_src/_static/searchfield_leftcap.png
doc_src/_static/searchfield_repeat.png
doc_src/_static/searchfield_rightcap.png
doc_src/_static/title_background.png
doc_src/_static/toc.js
doc_src/_static/triangle_closed.png
doc_src/_static/triangle_left.png
doc_src/_static/triangle_open.png
doc_src/_templates/layout.html
doc_src/reference/index.rst
doc_src/reference/settings.rst
docs/.buildinfo
docs/genindex.html
docs/getting_started.html
docs/index.html
docs/installation.html
docs/objects.inv
docs/one_blog_or_many.html
docs/relating_arbitrary_models.html
docs/search.html
docs/searchindex.js
docs/specifying_urls.html
docs/_sources/getting_started.txt
docs/_sources/index.txt
docs/_sources/installation.txt
docs/_sources/one_blog_or_many.txt
docs/_sources/relating_arbitrary_models.txt
docs/_sources/specifying_urls.txt
docs/_sources/reference/index.txt
docs/_sources/reference/settings.txt
docs/_static/basic.css
docs/_static/breadcrumb_background.png
docs/_static/default.css
docs/_static/doctools.js
docs/_static/documentation.png
docs/_static/file.png
docs/_static/header_sm_mid.png
docs/_static/jquery.js
docs/_static/minus.png
docs/_static/plus.png
docs/_static/pygments.css
docs/_static/scrn1.png
docs/_static/scrn2.png
docs/_static/searchfield_leftcap.png
docs/_static/searchfield_repeat.png
docs/_static/searchfield_rightcap.png
docs/_static/searchtools.js
docs/_static/sidebar.js
docs/_static/title_background.png
docs/_static/toc.js
docs/_static/triangle_closed.png
docs/_static/triangle_left.png
viewpoint.egg-info/PKG-INFO
viewpoint.egg-info/SOURCES.txt
viewpoint.egg-info/dependency_links.txt
viewpoint.egg-info/requires.txt
viewpoint.egg-info/top_level.txt
