Metadata-Version: 1.0
Name: viewpoint
Version: 0.9.8
Summary: A simple blog with hooks for categories, tinymce, tags and other things
Home-page: http://opensource.washingtontimes.com/projects/viewpoint/
Author: Justin Quick, Corey Oordt
Author-email: jquick@washingtontimes.com, coordt@washingtontimes.com
License: UNKNOWN
Platform: UNKNOWN
Classifier: Development Status :: 4 - Beta
Classifier: License :: OSI Approved :: Apache Software License
Classifier: Programming Language :: Python :: 2
Classifier: Environment :: Web Environment
Classifier: Intended Audience :: Developers
Classifier: Operating System :: OS Independent
Classifier: Topic :: Utilities
